faker_credit_score/__init__.py
faker_credit_score/_version.py
faker_credit_score-0.5.2.dist-info/METADATA
faker_credit_score-0.5.2.dist-info/WHEEL
faker_credit_score-0.5.2.dist-info/licenses/LICENSE
faker_credit_score-0.5.2.dist-info/RECORD
