Metadata-Version: 2.4
Name: faker-credit-score
Version: 0.5.2
Summary: Adds fake credit score data generation to Faker Python package.
Project-URL: Homepage, https://github.com/crd/faker-credit-score
Project-URL: Repository, https://github.com/crd/faker-credit-score
Author: Cory Donnelly
License: BSD 3-Clause License
License-File: LICENSE
Classifier: Intended Audience :: Developers
Classifier: License :: OSI Approved :: BSD License
Classifier: Programming Language :: Python :: 3
Classifier: Topic :: Software Development :: Testing
Requires-Python: >=3.9
Requires-Dist: faker>=37.8.0
